INSTALL
LICENSE
MANIFEST.in
README
setup.py
doc/clean.css
doc/email.png
doc/examples.html
doc/index.template.html
examples/README
examples/astat.py
examples/bd_client.py
examples/bd_serv.py
examples/cgishell.cgi
examples/chess.py
examples/chess2.py
examples/chess3.py
examples/df.py
examples/fix_cvs_files.py
examples/ftp.py
examples/hive.py
examples/monitor.py
examples/passmass.py
examples/python.py
examples/rippy.py
examples/script.py
examples/ssh_session.py
examples/ssh_tunnel.py
examples/sshls.py
examples/table_test.html
examples/topip.py
examples/uptime.py
pexpect/ANSI.py
pexpect/FSM.py
pexpect/__init__.py
pexpect/fdpexpect.py
pexpect/psh.py
pexpect/pxssh.py
pexpect/screen.py
pexpect/tests/PexpectTestCase.py
pexpect/tests/__init__.py
pexpect/tests/adhoc.py
pexpect/tests/echo_wait.py
pexpect/tests/exit1.py
pexpect/tests/getch.py
pexpect/tests/interact.py
pexpect/tests/pexpectTest.py
pexpect/tests/qa.py
pexpect/tests/sigwinch_report.py
pexpect/tests/test_ansi.py
pexpect/tests/test_command_list_split.py
pexpect/tests/test_constructor.py
pexpect/tests/test_ctrl_chars.py
pexpect/tests/test_destructor.py
pexpect/tests/test_dotall.py
pexpect/tests/test_expect.py
pexpect/tests/test_filedescriptor.py
pexpect/tests/test_interact.py
pexpect/tests/test_isalive.py
pexpect/tests/test_log.py
pexpect/tests/test_misc.py
pexpect/tests/test_missing_command.py
pexpect/tests/test_performance.py
pexpect/tests/test_run.py
pexpect/tests/test_run_out_of_pty.py
pexpect/tests/test_screen.py
pexpect/tests/test_timeout_pattern.py
pexpect/tests/test_winsize.py
pexpect/tests/ticker.py
pexpect_u.egg-info/PKG-INFO
pexpect_u.egg-info/SOURCES.txt
pexpect_u.egg-info/dependency_links.txt
pexpect_u.egg-info/top_level.txt